slackabet/__init__.py
slackabet/_version.py
slackabet/cli.py
slackabet-1.3.0.dist-info/METADATA
slackabet-1.3.0.dist-info/WHEEL
slackabet-1.3.0.dist-info/entry_points.txt
slackabet-1.3.0.dist-info/licenses/LICENSE.txt
slackabet-1.3.0.dist-info/RECORD
