Metadata-Version: 2.4
Name: slackabet
Version: 1.3.0
Summary: Convert text into Slack alphabet emoji
Project-URL: Changelog, https://github.com/hugovk/slackabet/releases
Project-URL: Homepage, https://github.com/hugovk/slackabet
Project-URL: Source, https://github.com/hugovk/slackabet
Author: Hugo van Kemenade
License: MIT
License-File: LICENSE.txt
Keywords: CLI,Slack,alphabet,convert,converter,emoji,text
Classifier: Development Status :: 4 - Beta
Classifier: Intended Audience :: Developers
Classifier: License :: OSI Approved :: MIT License
Classifier: Natural Language :: English
Classifier: Programming Language :: Python :: 3 :: Only
Classifier: Programming Language :: Python :: 3.9
Classifier: Programming Language :: Python :: 3.10
Classifier: Programming Language :: Python :: 3.11
Classifier: Programming Language :: Python :: 3.12
Classifier: Programming Language :: Python :: 3.13
Classifier: Programming Language :: Python :: 3.14
Classifier: Programming Language :: Python :: Implementation :: CPython
Classifier: Programming Language :: Python :: Implementation :: PyPy
Classifier: Topic :: Artistic Software
Classifier: Topic :: Text Processing
Requires-Python: >=3.9
Requires-Dist: pyperclip; platform_system != 'Linux'
Provides-Extra: tests
Requires-Dist: pytest; extra == 'tests'
Requires-Dist: pytest-cov; extra == 'tests'
